torrent_worker/__init__.py
torrent_worker/cli.py
torrent_worker/client.py
torrent_worker/config.py
torrent_worker/docker_compose_template.py
torrent_worker/github_downloader.py
torrent_worker/paths.py
torrent_worker/qbittorrent_conf.py
torrent_worker-1.0.1.dist-info/LICENSE
torrent_worker-1.0.1.dist-info/METADATA
torrent_worker-1.0.1.dist-info/WHEEL
torrent_worker-1.0.1.dist-info/entry_points.txt
torrent_worker-1.0.1.dist-info/top_level.txt
torrent_worker-1.0.1.dist-info/RECORD
