Metadata-Version: 2.1
Name: torrent-worker
Version: 1.0.1
Summary: Downloads torrents
License: BSD 3-Clause License
Keywords: Torrent,Worker,Distributed
Classifier: Programming Language :: Python :: 3
Requires-Python: >=3.10
License-File: LICENSE
Requires-Dist: colorama
Requires-Dist: appdirs
Requires-Dist: disklru
Requires-Dist: qbittorrent-api==2024.11.70
Requires-Dist: jinja2>=3.1.2
Requires-Dist: requests
Requires-Dist: rich
Provides-Extra: dev
Requires-Dist: ruff; extra == "dev"
Requires-Dist: flake8; extra == "dev"
Requires-Dist: mypy; extra == "dev"
Requires-Dist: pylint; extra == "dev"
Requires-Dist: pytest; extra == "dev"
Requires-Dist: black; extra == "dev"
Requires-Dist: isort; extra == "dev"
Requires-Dist: tox; extra == "dev"
Requires-Dist: requests; extra == "dev"
Requires-Dist: pytest-xdist; extra == "dev"
Requires-Dist: jinja2; extra == "dev"
